novatium/__init__.py
novatium/auto_classifier.py
novatium/auto_regressor.py
novatium-1.1.8.dist-info/licenses/LICENSE
novatium-1.1.8.dist-info/METADATA
novatium-1.1.8.dist-info/WHEEL
novatium-1.1.8.dist-info/top_level.txt
novatium-1.1.8.dist-info/RECORD
