Metadata-Version: 2.4
Name: novatium
Version: 1.1.8
Summary: Novatium — Cosmic-Grade Machine Learning with NovaAutoRegressor and NovaAutoClassifier for Tabular Data
Author: Praneeth Kumar Palepu
Author-email: praneeth.palepu@gmail.com
License: Apache-2.0
Project-URL: Homepage, https://github.com/<you>/novatium
Project-URL: Issues, https://github.com/<you>/novatium/issues
Keywords: machine-learning,regression,classification,fusion,ai
Classifier: Development Status :: 3 - Alpha
Classifier: Intended Audience :: Science/Research
Classifier: License :: OSI Approved :: Apache Software License
Classifier: Programming Language :: Python :: 3
Classifier: Programming Language :: Python :: 3 :: Only
Classifier: Topic :: Scientific/Engineering :: Artificial Intelligence
Requires-Python: >=3.9
License-File: LICENSE
Requires-Dist: numpy>=1.24
Requires-Dist: scikit-learn>=1.2
Dynamic: license-file
